processnamer/__init__.py
processnamer/example_use.py
processnamer/processnamer.py
processnamer-1.0.0.dist-info/METADATA
processnamer-1.0.0.dist-info/WHEEL
processnamer-1.0.0.dist-info/top_level.txt
processnamer-1.0.0.dist-info/RECORD
