Metadata-Version: 2.1
Name: processnamer
Version: 1.0.0
Summary: Library containing an object to name processes.
Home-page: https://eliservices.servehttp.com/docs/processnamer.html
Author: EliServices
Author-email: eliservices.server@gmail.com
License: Boost Software License 1.0 (BSL-1.0)
Platform: UNKNOWN
Classifier: Intended Audience :: Developers
Classifier: Development Status :: 5 - Production/Stable
Classifier: Environment :: Console
Classifier: License :: OSI Approved :: Boost Software License 1.0 (BSL-1.0)
Classifier: Programming Language :: Python :: 3.8
Classifier: Operating System :: POSIX :: Linux
Classifier: Topic :: Software Development :: Libraries :: Python Modules
